dataclasses.py
dataclasses-0.5.dist-info/DESCRIPTION.rst
dataclasses-0.5.dist-info/METADATA
dataclasses-0.5.dist-info/RECORD
dataclasses-0.5.dist-info/WHEEL
dataclasses-0.5.dist-info/metadata.json
dataclasses-0.5.dist-info/top_level.txt
